jonahlint/__init__.py
jonahlint/__main__.py
jonahlint/cli.py
jonahlint/profanity_analyzer.py
jonahlint/profanity_ast_checker.py
jonahlint/profanity_checker.py
jonahlint/profanity_report.py
jonahlint/profanity_visitor.py
jonahlint/sources_finder.py
jonahlint/resources/profane_words.txt
jonahlint-0.0.2.dist-info/LICENSE
jonahlint-0.0.2.dist-info/METADATA
jonahlint-0.0.2.dist-info/WHEEL
jonahlint-0.0.2.dist-info/entry_points.txt
jonahlint-0.0.2.dist-info/top_level.txt
jonahlint-0.0.2.dist-info/RECORD
