Metadata-Version: 2.1
Name: jonahlint
Version: 0.0.2
Summary: Profanity linter for Python
Home-page: UNKNOWN
Author: Sagi Shadur
Author-email: saroad2@gmail.com
Maintainer: Sagi Shadur
Maintainer-email: saroad2@gmail.com
License: Apache License
Keywords: linter,profanity,code,analysis
Platform: any
Classifier: Development Status :: 3 - Alpha
Classifier: Intended Audience :: Developers
Classifier: License :: OSI Approved :: BSD License
Classifier: Operating System :: OS Independent
Classifier: Programming Language :: Python :: 3
Classifier: Programming Language :: Python :: 3.7
Classifier: Programming Language :: Python :: 3.8
Classifier: Programming Language :: Python :: 3.9
Classifier: Programming Language :: Python :: 3 :: Only
Classifier: Topic :: Software Development
Classifier: Topic :: Utilities
Requires-Python: >=3.6
Requires-Dist: click (>=7.1.2)
